bee_utils/__init__.py
bee_utils/__main__.py
bee_utils/bee_utils.py
bee_utils-0.1.0a0.dist-info/entry_points.txt
bee_utils-0.1.0a0.dist-info/LICENSE
bee_utils-0.1.0a0.dist-info/WHEEL
bee_utils-0.1.0a0.dist-info/METADATA
bee_utils-0.1.0a0.dist-info/RECORD
